PyDamp/PyDampCheck.py
PyDamp/PyDamp_Run.py
PyDamp/PyDamp_SQLconnection.py
PyDamp/PyDamp_Tests.py
PyDamp/__init__.py
PyDamp/tests/PyDamp_Tests.py
PyDamp/tests/__init__.py
PyDamp-0.0.15.data/data/PyDamp/Example_Product_input.yaml
PyDamp-0.0.15.data/data/PyDamp/PyDamp_Server.yaml
PyDamp-0.0.15.dist-info/LICENSE
PyDamp-0.0.15.dist-info/METADATA
PyDamp-0.0.15.dist-info/WHEEL
PyDamp-0.0.15.dist-info/top_level.txt
PyDamp-0.0.15.dist-info/RECORD
